ragchat/__init__.py
ragchat/document_loader.py
ragchat-0.1.dist-info/METADATA
ragchat-0.1.dist-info/WHEEL
ragchat-0.1.dist-info/top_level.txt
ragchat-0.1.dist-info/RECORD
